{
    "data": [
        {
            "id": "65679bf6-5641-47d7-90c0-ef8d604cea70",
            "employee": {
                "id": "0a1a5c04-0be9-48b1-82bf-5de801bdb722",
                "employeeNumber": "2",
                "employeeName": "Margaret Wilson"
            },
            "startDate": "2023-08-04",
            "endDate": "2023-08-30"
        },
        {
            "id": "bf406e1c-b155-42d8-a052-d5bfd4058835",
            "employee": {
                "id": "23d46b63-e7cc-44b2-8479-6b8e999fc764",
                "employeeNumber": "3",
                "employeeName": "Ashley Scott"
            },
            "startDate": "2023-08-17",
            "endDate": null
        },
        {
            "id": "920a95e0-d846-4dd9-a8c8-76fa79876f2f",
            "employee": {
                "id": "22af8d5c-6bf3-46b6-8515-38284b99e144",
                "employeeNumber": "4",
                "employeeName": "Sandra Anderson"
            },
            "startDate": "2023-08-03",
            "endDate": null
        },
        {
            "id": "71e00b89-d2c7-4756-89f5-504b195b2e23",
            "employee": {
                "id": "17b28efc-ad5c-41ef-83fa-86142aa6f8dc",
                "employeeNumber": "7",
                "employeeName": "Michael White"
            },
            "startDate": "2023-08-01",
            "endDate": null
        }
    ],
    "pageNumber": 1,
    "pageSize": 100,
    "firstPage": "https://api.samardash.com/mock/api/v1/psa/projects/97fb2578-c000-4ad0-9757-d4b0dba65f4c/allocations?pageNumber=1&pageSize=100",
    "lastPage": "https://api.samardash.com/mock/api/v1/psa/projects/97fb2578-c000-4ad0-9757-d4b0dba65f4c/allocations?pageNumber=1&pageSize=100",
    "totalPages": 1,
    "totalRecords": 4,
    "nextPage": null,
    "previousPage": null,
    "succeeded": true,
    "message": null,
    "errors": null
}